odoo/addons/mrp_subcontracting_resupply_link/README.rst
odoo/addons/mrp_subcontracting_resupply_link/__init__.py
odoo/addons/mrp_subcontracting_resupply_link/__manifest__.py
odoo/addons/mrp_subcontracting_resupply_link/i18n/es.po
odoo/addons/mrp_subcontracting_resupply_link/i18n/it.po
odoo/addons/mrp_subcontracting_resupply_link/i18n/mrp_subcontracting_resupply_link.pot
odoo/addons/mrp_subcontracting_resupply_link/models/__init__.py
odoo/addons/mrp_subcontracting_resupply_link/models/purchase_order.py
odoo/addons/mrp_subcontracting_resupply_link/models/stock_picking.py
odoo/addons/mrp_subcontracting_resupply_link/readme/CONTRIBUTORS.rst
odoo/addons/mrp_subcontracting_resupply_link/readme/DESCRIPTION.rst
odoo/addons/mrp_subcontracting_resupply_link/readme/USAGE.rst
odoo/addons/mrp_subcontracting_resupply_link/static/description/icon.png
odoo/addons/mrp_subcontracting_resupply_link/static/description/index.html
odoo/addons/mrp_subcontracting_resupply_link/tests/__init__.py
odoo/addons/mrp_subcontracting_resupply_link/tests/test_mrp_subcontracting_resupply_link.py
odoo/addons/mrp_subcontracting_resupply_link/views/purchase_order_view.xml
odoo/addons/mrp_subcontracting_resupply_link/views/stock_picking_view.xml
odoo14_addon_mrp_subcontracting_resupply_link-14.0.1.0.1.dev7.dist-info/METADATA
odoo14_addon_mrp_subcontracting_resupply_link-14.0.1.0.1.dev7.dist-info/WHEEL
odoo14_addon_mrp_subcontracting_resupply_link-14.0.1.0.1.dev7.dist-info/top_level.txt
odoo14_addon_mrp_subcontracting_resupply_link-14.0.1.0.1.dev7.dist-info/RECORD
